blogsimi/__init__.py
blogsimi/__main__.py
blogsimi/cli.py
blogsimi/core.py
blogsimi-0.0.6.dist-info/licenses/LICENSE
blogsimi-0.0.6.dist-info/METADATA
blogsimi-0.0.6.dist-info/WHEEL
blogsimi-0.0.6.dist-info/entry_points.txt
blogsimi-0.0.6.dist-info/top_level.txt
blogsimi-0.0.6.dist-info/RECORD
