Metadata-Version: 2.4
Name: blogsimi
Version: 0.0.6
Summary: Semantic related-article indexer and generator for static blogs.
Author-email: Thomas Spielauer <pypipackages01@tspi.at>
License-Expression: BSD-3-Clause
Keywords: semantic-search,blog,pgvector,recommendations
Classifier: Programming Language :: Python :: 3
Classifier: Programming Language :: Python :: 3.9
Classifier: Programming Language :: Python :: 3.10
Classifier: Programming Language :: Python :: 3.11
Classifier: Programming Language :: Python :: 3.12
Classifier: Intended Audience :: Developers
Classifier: Topic :: Internet :: WWW/HTTP
Classifier: Topic :: Scientific/Engineering :: Artificial Intelligence
Requires-Python: >=3.9
License-File: LICENSE
Requires-Dist: beautifulsoup4>=4.9
Requires-Dist: markdownify>=0.12
Requires-Dist: psycopg2-binary>=2.9
Requires-Dist: requests>=2.28
Dynamic: license-file
